LICENSE
MANIFEST.in
README.rst
setup.py
azure_storage_logging/__init__.py
azure_storage_logging/handlers.py
azure_storage_logging_updated.egg-info/PKG-INFO
azure_storage_logging_updated.egg-info/SOURCES.txt
azure_storage_logging_updated.egg-info/dependency_links.txt
azure_storage_logging_updated.egg-info/requires.txt
azure_storage_logging_updated.egg-info/top_level.txt