Metadata-Version: 1.1
Name: azure-storage-logging-updated
Version: 0.6.0
Summary: Logging handlers to send logs to Microsoft Azure Storage
Home-page: https://github.com/AbianG/azure-storage-logging_updated
Author: Abian Rodriguez
Author-email: abiangrodriguez@protonmail.com
License: Apache License 2.0
Keywords: azure logging
Platform: UNKNOWN
Classifier: Development Status :: 4 - Beta
Classifier: License :: OSI Approved :: Apache Software License
Classifier: Programming Language :: Python
Classifier: Programming Language :: Python :: 2
Classifier: Programming Language :: Python :: 2.7
Classifier: Programming Language :: Python :: 3
Classifier: Programming Language :: Python :: 3.3
Classifier: Programming Language :: Python :: 3.4
Classifier: Programming Language :: Python :: 3.5
Classifier: Topic :: System :: Logging
